gemseo_matlab/__init__.py
gemseo_matlab/engine.py
gemseo_matlab/license_manager.py
gemseo_matlab/matlab_data_processor.py
gemseo_matlab/matlab_discipline.py
gemseo_matlab/matlab_parser.py
gemseo_matlab/matlab_files/Logger.m
gemseo_matlab/matlab_files/licenseControl.m
gemseo_matlab-2.0.4.dist-info/licenses/LICENSE.txt
gemseo_matlab-2.0.4.dist-info/METADATA
gemseo_matlab-2.0.4.dist-info/WHEEL
gemseo_matlab-2.0.4.dist-info/entry_points.txt
gemseo_matlab-2.0.4.dist-info/top_level.txt
gemseo_matlab-2.0.4.dist-info/RECORD
