Metadata-Version: 2.4
Name: gemseo-matlab
Version: 2.0.4
Summary: MATLAB wrapper for GEMSEO
Author-email: GEMSEO developers <contact@gemseo.org>
License-Expression: LGPL-3.0
Project-URL: Homepage, https://gemseo.org
Project-URL: Source, https://gitlab.com/gemseo/dev/gemseo-matlab
Project-URL: Issues, https://gitlab.com/gemseo/dev/gemseo-matlab/-/issues
Classifier: Intended Audience :: Science/Research
Classifier: Topic :: Scientific/Engineering
Classifier: Operating System :: POSIX :: Linux
Classifier: Operating System :: MacOS
Classifier: Operating System :: Microsoft :: Windows
Classifier: Programming Language :: Python :: 3 :: Only
Classifier: Programming Language :: Python :: 3.10
Classifier: Programming Language :: Python :: 3.11
Classifier: Programming Language :: Python :: 3.12
Classifier: Programming Language :: Python :: 3.13
Requires-Python: <3.14,>=3.10
License-File: LICENSE.txt
Requires-Dist: gemseo[all]<7,>=6.3
Requires-Dist: numpy
Requires-Dist: scipy
Requires-Dist: strenum
Dynamic: license-file
